variosSort/__init__.py
variosSort/variousSort.py
variousSort-0.0.3.dist-info/LICENSE
variousSort-0.0.3.dist-info/METADATA
variousSort-0.0.3.dist-info/WHEEL
variousSort-0.0.3.dist-info/top_level.txt
variousSort-0.0.3.dist-info/RECORD
